{
	"addonId": "tonysEnhancements",
	"displayName": "Tony's enhancements",
	"URL": "https://github.com/mltony/nvda-tonys-enhancements/releases/download/1.21/tonysEnhancements-1.21.nvda-addon",
	"description": "Various NVDA enhancements.",
	"sha256": "91d48098a2dc8d8b79000c2825a7abfe64ab7af54596902ec0950049a7afc53a",
	"addonVersionName": "1.21",
	"addonVersionNumber": {
		"major": 1,
		"minor": 21,
		"patch": 0
	},
	"minNVDAVersion": {
		"major": 2024,
		"minor": 2,
		"patch": 0
	},
	"lastTestedVersion": {
		"major": 2024,
		"minor": 2,
		"patch": 0
	},
	"channel": "stable",
	"publisher": "Tony Malykh",
	"sourceURL": "https://github.com/mltony/nvda-tonys-enhancements/",
	"license": "GPL v2",
	"homepage": "https://github.com/mltony/nvda-tonys-enhancements/",
	"licenseURL": "https://www.gnu.org/licenses/gpl-2.0.html",
	"submissionTime": 1726877557000,
	"translations": [
		{
			"language": "es",
			"displayName": "Mejoras de Tony",
			"description": "Diversas mejoras para NVDA."
		},
		{
			"language": "fi",
			"displayName": "Tonyn laajennukset",
			"description": "Useita NVDA:n laajennuksia"
		},
		{
			"language": "fr",
			"displayName": "Tony's enhancements",
			"description": "Diverses améliorations pour NVDA."
		},
		{
			"language": "pl",
			"displayName": "Tony's enhancements",
			"description": "Różne usprawnienia dla NVDA."
		},
		{
			"language": "pt_PT",
			"displayName": "Melhorias do Tony",
			"description": "Várias melhorias no NVDA."
		},
		{
			"language": "ru",
			"displayName": "Улучшения от Тони",
			"description": "Различные усовершенствования для NVDA."
		},
		{
			"language": "tr",
			"displayName": "Tony'nin Geliştirmeleri",
			"description": "Çeşitli NVDA geliştirmeleri."
		},
		{
			"language": "uk",
			"displayName": "Tony's enhancements",
			"description": "Різні покращення NVDA."
		},
		{
			"language": "zh_CN",
			"displayName": "Tony 的增强",
			"description": "NVDA 的各种增强功能。"
		}
	],
	"reviewUrl": "https://github.com/nvaccess/addon-datastore/discussions/3872"
}
