{
	"addonId": "gestureDuplicate",
	"displayName": "gestureDuplicate",
	"URL": "https://github.com/chaichaimee/gestureDuplicate/releases/download/v2025.12/gestureDuplicate-v2025.12.nvda-addon",
	"description": "Identifies and manages conflicting keyboard shortcuts in your NVDA configuration",
	"sha256": "21dab4a0bfaf9b585303cc2a25c0e91fc2676f6853640b5beb99f4df25ee415f",
	"addonVersionName": "2025.12",
	"addonVersionNumber": {
		"major": 2025,
		"minor": 12,
		"patch": 0
	},
	"minNVDAVersion": {
		"major": 2022,
		"minor": 4,
		"patch": 0
	},
	"lastTestedVersion": {
		"major": 2025,
		"minor": 3,
		"patch": 0
	},
	"channel": "stable",
	"publisher": "chaichaimee",
	"sourceURL": "https://github.com/chaichaimee/gestureDuplicate",
	"license": "GPL v2",
	"homepage": "https://github.com/chaichaimee/gestureDuplicate",
	"licenseURL": "https://www.gnu.org/licenses/gpl-2.0.html",
	"submissionTime": 1767057394000,
	"translations": []
}