{
  "addonId": "referenceToneTuner",
  "displayName": "Reference Tone Tuner",
  "URL": "https://github.com/leandro-sds/Reference-Tone-Tuner/releases/download/2026.07.06/referenceToneTuner-2026.07.06.nvda-addon",
  "description": "Afinador por tons de referência para violão/guitarra.\nUse as teclas 1 a 6 para tocar as cordas e afine de ouvido até coincidir.\nPressione F1 para ajuda, R para repetir em loop e A/D para ajustar o intervalo do loop.",
  "sha256": "0a065584101ef481f11e60e7f57f46ff32bdceb54cfa2317f88c6ca26c43d532",
  "addonVersionName": "2026.07.06",
  "addonVersionNumber": {
    "major": 2026,
    "minor": 7,
    "patch": 6
  },
  "minNVDAVersion": {
    "major": 2024,
    "minor": 1,
    "patch": 0
  },
  "lastTestedVersion": {
    "major": 2026,
    "minor": 1,
    "patch": 0
  },
  "channel": "stable",
  "publisher": "Leandro Souza",
  "sourceURL": "https://github.com/leandro-sds/Reference-Tone-Tuner",
  "license": "GPL v2",
  "homepage": "https://github.com/leandro-sds/Reference-Tone-Tuner",
  "changelog": "* Novo: intervalo do loop agora é ajustável com as teclas A (aumentar) e D (diminuir), padrão de 2,0 segundos.\n* Correção: ao tocar uma corda/acorde único sem loop, a tecla Esc às vezes não fechava a janela na primeira tentativa.\n* Menos falas desnecessárias ao abrir a janela (intervalo do loop e atalho do R só são anunciados quando usados).",
  "licenseURL": "https://www.gnu.org/licenses/gpl-2.0.html",
  "submissionTime": 1783347952000,
  "translations": [],
  "vtScanUrl": "https://www.virustotal.com/gui/file/0a065584101ef481f11e60e7f57f46ff32bdceb54cfa2317f88c6ca26c43d532",
  "scanResults": {
    "virusTotal": [
      {
        "_id": "0a065584101ef481f11e60e7f57f46ff32bdceb54cfa2317f88c6ca26c43d532",
        "_type": "file",
        "filecondis": {
          "dhash": "0000000001030300",
          "raw_md5": "10fed43ddc292e3621d24aa50c690e84"
        },
        "first_submission_date": 1783347955,
        "last_analysis_results": {},
        "last_analysis_stats": {
          "confirmed-timeout": 0,
          "failure": 0,
          "harmless": 0,
          "malicious": 0,
          "suspicious": 0,
          "timeout": 0,
          "type-unsupported": 0,
          "undetected": 0
        },
        "last_modification_date": 1783347956,
        "last_submission_date": 1783347955,
        "md5": "2c0c5fc8ea9aae4661228170944d2466",
        "names": [],
        "reputation": 0,
        "sha1": "547bb383c37c64331ae965b841cb103378727a66",
        "sha256": "0a065584101ef481f11e60e7f57f46ff32bdceb54cfa2317f88c6ca26c43d532",
        "size": 2694661,
        "tags": [],
        "times_submitted": 1,
        "total_votes": {
          "harmless": 0,
          "malicious": 0
        },
        "type_description": "unknown",
        "type_tags": [],
        "unique_sources": 1
      }
    ]
  },
  "reviewUrl": "https://github.com/nvaccess/addon-datastore/discussions/8262"
}
