{
	"addonId": "Open_Bible",
	"displayName": "Open Bible",
	"URL": "https://github.com/leandro-sds/Open_Bible/releases/download/2026.04.01/Open_Bible-2026.04.01.nvda-addon",
	"description": "Este add-on permite a leitura da Bíblia Sagrada no NVDA em várias versões (arquivos JSON).\n\t\tVocê pode navegar por livro, capítulo e versículo, pesquisar, favoritar, anotar e copiar/compartilhar versículos.",
	"sha256": "29968366b2ec172daf3556d3904acd25b3569ebd4f8fed7924d591cfbf8eacc9",
	"addonVersionName": "2026.04.01",
	"addonVersionNumber": {
		"major": 2026,
		"minor": 4,
		"patch": 1
	},
	"minNVDAVersion": {
		"major": 2024,
		"minor": 1,
		"patch": 0
	},
	"lastTestedVersion": {
		"major": 2025,
		"minor": 3,
		"patch": 3
	},
	"channel": "stable",
	"publisher": "Leandro Souza",
	"sourceURL": "https://github.com/leandro-sds/Open_Bible/",
	"license": "GPL v2",
	"homepage": "https://github.com/leandro-sds/Open-Bible",
	"changelog": "Melhorias desta versão:\nnavegação entre livros sem voltar ao índice,\nbips de limite mais discretos,\nir direto a capítulo ou versículo com F5\nlista de livros sem travamentos.",
	"licenseURL": "https://www.gnu.org/licenses/gpl-2.0.html",
	"submissionTime": 1774991560000,
	"translations": []
}