{"addonId": "wordCount", "displayName": "Compter les \u00e9l\u00e9ments du texte s\u00e9lectionn\u00e9", "URL": "https://github.com/ruifontes/wordCount/releases/download/2023.09.06/wordCount-2023.09.06.nvda-addon", "description": "annonce le nombre de mots, de caract\u00e8res et de paragraphes du texte s\u00e9lectionn\u00e9 en appuyant sur Control+Maj+F12.\n\tIl peut \u00e9galement cr\u00e9er une liste des mots utilis\u00e9s, class\u00e9s par nombre d'occurrences ou par ordre alphab\u00e9tique, afficher les lignes contenant un mot et enfin se d\u00e9placer \u00e0 une ligne sp\u00e9cifique, en appuyant sur Ctrl+Maj+F11.", "sha256": "e646a31a163ea0e25307d4ca19dd6a049a26cfec4e910c9c6c5963be7521400f", "addonVersionName": "2023.09.06", "addonVersionNumber": {"major": 2023, "minor": 9, "patch": 6}, "minNVDAVersion": {"major": 2019, "minor": 3, "patch": 0}, "lastTestedVersion": {"major": 2023, "minor": 1, "patch": 0}, "channel": "stable", "publisher": "Rui Fontes", "sourceURL": "https://github.com/ruifontes/wordCount", "license": "GPL v2", "homepage": "https://github.com/ruifontes/wordcount", "licenseURL": "https://www.gnu.org/licenses/gpl-2.0.html"}