{"addonId": "remotePlusPlus", "displayName": "Remote++", "URL": "https://github.com/cary-rowen/remotePlusPlus/releases/download/0.4.0/remotePlusPlus-0.4.0.nvda-addon", "description": "Enhances NVDA Remote with productivity features for power users.", "sha256": "cdc5900059437cf953d01440f526bd406aab3f4a321cd05f6c04575879bed271", "addonVersionName": "0.4.0", "addonVersionNumber": {"major": 0, "minor": 4, "patch": 0}, "minNVDAVersion": {"major": 2025, "minor": 1, "patch": 0}, "lastTestedVersion": {"major": 2025, "minor": 3, "patch": 2}, "channel": "stable", "publisher": "Cary-rowen <manchen_0528@outlook.com>", "sourceURL": "https://github.com/cary-rowen/remotePlusPlus/", "license": "GPL v2", "homepage": "https://github.com/cary-rowen/remotePlusPlus", "changelog": "## 0.4.0\n\n* Remove the \"Connect\" button from the Connection Manager dialog (keep in context menu).\n* Remove the \"Copy link\" button from the Connection Manager dialog (keep in context menu).\n* Add Ctrl+C keyboard shortcut for copy link functionality.\n* Gestures and accelerator keys have been changed; see the add-on documentation for details.", "licenseURL": "https://www.gnu.org/licenses/gpl-2.0.html", "submissionTime": 1768724241000}