{"addonId": "eMule", "displayName": "eMule", "URL": "https://github.com/nvdaes/emule/releases/download/24.2.0/eMule-24.2.0.nvda-addon", "description": "\u041f\u043e\u0434\u043e\u0431\u0440\u044f\u0432\u0430 \u0434\u043e\u0441\u0442\u044a\u043f\u043d\u043e\u0441\u0442\u0442\u0430 \u043d\u0430 eMule \u043f\u0440\u0438 \u0440\u0430\u0431\u043e\u0442\u0430 \u0441 NVDA.\neMule \u0435 P2P \u043f\u0440\u043e\u0433\u0440\u0430\u043c\u0430 \u0437\u0430 \u0442\u044a\u0440\u0441\u0435\u043d\u0435 \u0438 \u0441\u043f\u043e\u0434\u0435\u043b\u044f\u043d\u0435 \u043d\u0430 \u0444\u0430\u0439\u043b\u043e\u0432\u0435.\n\u041c\u043e\u0436\u0435 \u0434\u0430 \u043f\u043e\u043b\u0443\u0447\u0438\u0442\u0435 \u043f\u043e\u0432\u0435\u0447\u0435 \u0438\u043d\u0444\u043e\u0440\u043c\u0430\u0446\u0438\u044f \u0437\u0430 eMule \u043d\u0430 \u0430\u0434\u0440\u0435\u0441\nhttp://www.emule-project.net", "sha256": "13e2fd548a53724d36ca93a62fef8dac390fa5104ef3a80919a253ecc346cb27", "addonVersionName": "24.2.0", "addonVersionNumber": {"major": 24, "minor": 2, "patch": 0}, "minNVDAVersion": {"major": 2026, "minor": 1, "patch": 0}, "lastTestedVersion": {"major": 2026, "minor": 1, "patch": 0}, "channel": "beta", "publisher": "nvdaes", "sourceURL": "https://github.com/nvdaes/emule/releases/tag/24.2.0", "license": "GPL v2", "homepage": "https://github.com/nvdaes/emule", "changelog": "* Compatible with NVDA 2026.1.", "licenseURL": "https://www.gnu.org/licenses/gpl-2.0.html", "submissionTime": 1772790887000, "vtScanUrl": "https://www.virustotal.com/gui/file/13e2fd548a53724d36ca93a62fef8dac390fa5104ef3a80919a253ecc346cb27", "scanResults": {"codeQL-warnings": [], "codeQL-errors": [], "virusTotal": [{"_id": "13e2fd548a53724d36ca93a62fef8dac390fa5104ef3a80919a253ecc346cb27", "_type": "file", "filecondis": {"dhash": "0000081c1e1d0400", "raw_md5": "4ed97bf535cd3c8ea877f0bfc45a40a0"}, "first_submission_date": 1772790903, "last_analysis_results": {}, "last_analysis_stats": {"confirmed-timeout": 0, "failure": 0, "harmless": 0, "malicious": 0, "suspicious": 0, "timeout": 0, "type-unsupported": 0, "undetected": 0}, "last_modification_date": 1772790904, "last_submission_date": 1772790903, "md5": "595f77c9476e8e18073daff564ffff0a", "names": [], "reputation": 0, "sha1": "ae0ae66370667ed236e162b26fb41df8b94e2e0b", "sha256": "13e2fd548a53724d36ca93a62fef8dac390fa5104ef3a80919a253ecc346cb27", "size": 225650, "tags": [], "times_submitted": 1, "total_votes": {"harmless": 0, "malicious": 0}, "type_description": "unknown", "type_tags": [], "unique_sources": 1}]}, "reviewUrl": "https://github.com/nvaccess/addon-datastore/discussions/2118"}