{
	"addonId": "phoneticPunctuation",
	"displayName": "Earcons and speech rules",
	"URL": "https://github.com/mltony/nvda-phonetic-punctuation/releases/download/v3.0.3/phoneticPunctuation-3.0.3.nvda-addon",
	"description": "Earcons and speech rules add-on (previously known as phonetic punctuation).\nAllows to set up earcons for words, characters, roles, states, formatting information.\nPlease check out documentation for the full list of available speech rules.",
	"sha256": "169c3ac471bb597f3e53f865b016da9755bbcf7cccd280d7a336e19906d2720f",
	"addonVersionName": "3.0.3",
	"addonVersionNumber": {
		"major": 3,
		"minor": 0,
		"patch": 3
	},
	"minNVDAVersion": {
		"major": 2019,
		"minor": 3,
		"patch": 0
	},
	"lastTestedVersion": {
		"major": 2024,
		"minor": 1,
		"patch": 0
	},
	"channel": "stable",
	"publisher": "Tony Malykh",
	"sourceURL": "https://github.com/mltony/nvda-phonetic-punctuation/releases/download/v3.0.3/phoneticPunctuation-3.0.3.nvda-addon",
	"license": "GPL v2",
	"homepage": "https://github.com/mltony/nvda-phonetic-punctuation/",
	"licenseURL": "https://www.gnu.org/licenses/gpl-2.0.html",
	"submissionTime": 1735588964000,
	"translations": [],
	"reviewUrl": "https://github.com/nvaccess/addon-datastore/discussions/3663",
	"vtScanUrl": "https://www.virustotal.com/gui/file/169c3ac471bb597f3e53f865b016da9755bbcf7cccd280d7a336e19906d2720f"
}
