{
	"addonId": "phoneticPunctuation",
	"displayName": "Earcons and speech rules",
	"URL": "https://github.com/mltony/nvda-phonetic-punctuation/releases/download/v3.0/phoneticPunctuation-3.0.nvda-addon",
	"description": "Earcons and speech rules add-on (previously known as phonetic punctuation).\nAllows to set up earcons for words, characters, roles, states, formatting information.\nPlease check out documentation for the full list of available speech rules.",
	"sha256": "33ba74cfca27af8ef41002568ed43db3a7576623db80fe7e79b51f2e0288bdb9",
	"addonVersionName": "3.0",
	"addonVersionNumber": {
		"major": 3,
		"minor": 0,
		"patch": 0
	},
	"minNVDAVersion": {
		"major": 2019,
		"minor": 3,
		"patch": 0
	},
	"lastTestedVersion": {
		"major": 2024,
		"minor": 1,
		"patch": 0
	},
	"channel": "stable",
	"publisher": "Tony Malykh",
	"sourceURL": "https://github.com/mltony/nvda-phonetic-punctuation/releases/download/v3.0/phoneticPunctuation-3.0.nvda-addon",
	"license": "GPL v2",
	"homepage": "https://github.com/mltony/nvda-phonetic-punctuation/",
	"licenseURL": "https://www.gnu.org/licenses/gpl-2.0.html",
	"submissionTime": 1735349461000,
	"translations": []
}