{
  "addonId": "placeMarkers",
  "displayName": "Place markers",
  "URL": "https://github.com/nvdaes/placeMarkers/releases/download/52.1.0/placeMarkers-52.1.0.nvda-addon",
  "description": "Add-on for setting place markers on specific virtual documents",
  "sha256": "7f46b0804a45272d54bf20b9abe0a522d635f131702561cdf4c4942e1ee47375",
  "addonVersionName": "52.1.0",
  "addonVersionNumber": {
    "major": 52,
    "minor": 1,
    "patch": 0
  },
  "minNVDAVersion": {
    "major": 2026,
    "minor": 1,
    "patch": 0
  },
  "lastTestedVersion": {
    "major": 2026,
    "minor": 1,
    "patch": 0
  },
  "channel": "beta",
  "publisher": "nvdaes",
  "sourceURL": "https://github.com/nvdaes/placeMarkers/releases/tag/52.1.0",
  "license": "GPL v2",
  "homepage": "https://github.com/nvdaes/placeMarkers",
  "changelog": "* Bookmarks will be stored in yaml files.",
  "licenseURL": "https://www.gnu.org/licenses/gpl-2.0.html",
  "submissionTime": 1781447281000,
  "translations": [
    {
      "language": "ar",
      "displayName": "علامات مرجعية",
      "description": "إضافة لوضع علامات مرجعية داخل مستندات نمط التصفح",
      "changelog": "* Bookmarks will be stored in yaml files."
    },
    {
      "language": "bg",
      "displayName": "Позиционни маркери (Place markers)",
      "description": "Добавка за задаване на позиционни маркери за определени виртуални документи",
      "changelog": "* Bookmarks will be stored in yaml files."
    },
    {
      "language": "da",
      "displayName": "Stedmærker",
      "description": "Tilføjelsesprogram til at sætte stedmærker i specifikke virtuelle dokumenter",
      "changelog": "* Bookmarks will be stored in yaml files."
    },
    {
      "language": "de",
      "displayName": "Lesezeichen",
      "description": "Erweiterung zum Setzen von Lesezeichen in virtuellen Ansichten",
      "changelog": "* Bookmarks will be stored in yaml files."
    },
    {
      "language": "de_CH",
      "displayName": "Lesezeichen",
      "description": "Erweiterung zum Einstellen der Lesezeichen in virtuellen Ansichten.",
      "changelog": "* Bookmarks will be stored in yaml files."
    },
    {
      "language": "es",
      "displayName": "PlaceMarkers",
      "description": "Complemento para establecer las marcas en páginas Web y documentos virtuales específicos",
      "changelog": "* Bookmarks will be stored in yaml files."
    },
    {
      "language": "es_CO",
      "displayName": "PlaceMarkers",
      "description": "Complemento para establecer las marcas en páginas Web y documentos virtuales específicos.",
      "changelog": "* Bookmarks will be stored in yaml files."
    },
    {
      "language": "fa",
      "displayName": "نشان‌گذاری‌ها",
      "description": "افزونه‌ای برای تنظیمِ نشان‌گذاری‌ها در اسنادِ مجازی",
      "changelog": "* Bookmarks will be stored in yaml files."
    },
    {
      "language": "fi",
      "displayName": "Paikkamerkit",
      "description": "Lisäosa sivukohtaisten paikkamerkkien määrittämiseen",
      "changelog": "* Bookmarks will be stored in yaml files."
    },
    {
      "language": "fr",
      "displayName": "Marqueurs de position",
      "description": "Extension permettant de placer des marqueurs de position dans des documents spécifiques",
      "changelog": "* Bookmarks will be stored in yaml files."
    },
    {
      "language": "gl",
      "displayName": "Place markers",
      "description": "Complemento para fixar marcas en documentos virtuais específicos",
      "changelog": "* Bookmarks will be stored in yaml files."
    },
    {
      "language": "he",
      "displayName": "סימניות",
      "description": "תוסף זה מיועד להגדיר סימניות במסמכים וירטואלים נבחרים",
      "changelog": "* Bookmarks will be stored in yaml files."
    },
    {
      "language": "hr",
      "displayName": "Oznake pozicija",
      "description": "Dodatak koji omogućuje postavljanje oznaka pozicija na određene virtualne dokumente",
      "changelog": "* Bookmarks will be stored in yaml files."
    },
    {
      "language": "hu",
      "displayName": "Helyjelzők",
      "description": "Kiegészítő a helyjelzők elhelyezésére virtuális dokumentumokban",
      "changelog": "* Bookmarks will be stored in yaml files."
    },
    {
      "language": "it",
      "displayName": "PlaceMarkers",
      "description": "Componente aggiuntivo per impostare Segnaposto in pagine Web e documenti virtuali",
      "changelog": "* Bookmarks will be stored in yaml files."
    },
    {
      "language": "ja",
      "displayName": "Place markers",
      "description": "ドキュメントにプレイスマーカーを設定できます",
      "changelog": "* Bookmarks will be stored in yaml files."
    },
    {
      "language": "ko",
      "displayName": "북마크",
      "description": "가상 문서에 북마크를 지정하는 추가 기능",
      "changelog": "* Bookmarks will be stored in yaml files."
    },
    {
      "language": "ne",
      "displayName": "स्थान चिनो ",
      "description": "विशेष अवास्तविक कागजातहरूमा स्थान चिनो अनुकूलन गर्ने उपकर्मी ।",
      "changelog": "* Bookmarks will be stored in yaml files."
    },
    {
      "language": "nl",
      "displayName": "Plaats markeringen",
      "description": "Add-on om plaats markeringen in specifieke virtuele documenten aan te brengen",
      "changelog": "* Bookmarks will be stored in yaml files."
    },
    {
      "language": "pl",
      "displayName": "Znaczniki miejsca",
      "description": "Dodatek pozwalający ustawić znaczniki miejsca wewnątrz określonych dokumentów wirtualnych",
      "changelog": "* Bookmarks will be stored in yaml files."
    },
    {
      "language": "pt_BR",
      "displayName": "Marcadores de lugar",
      "description": "Complemento para criar marcadores de lugar em documentos virtuais específicos",
      "changelog": "* Bookmarks will be stored in yaml files."
    },
    {
      "language": "pt_PT",
      "displayName": "Marcadores de lugar",
      "description": "Extra para definir marcadores de lugar em documentos virtuais específicos",
      "changelog": "* Bookmarks will be stored in yaml files."
    },
    {
      "language": "ro",
      "displayName": "Marcaje locație",
      "description": "Supliment pentru plasarea de marcaje de locație pe documente virtuale specifice",
      "changelog": "* Bookmarks will be stored in yaml files."
    },
    {
      "language": "ru",
      "displayName": "Place markers",
      "description": "Дополнение для установки закладок в документы с виртуальном буфером",
      "changelog": "* Bookmarks will be stored in yaml files."
    },
    {
      "language": "sk",
      "displayName": "Záložky",
      "description": "umožňuje pridávať záložky do dokumentov zobrazených v režime prehliadania ",
      "changelog": "* Bookmarks will be stored in yaml files."
    },
    {
      "language": "sl",
      "displayName": "Prostorske označbe",
      "description": "Dodatek za postavitev prostorskih označb v izbranih navideznih dokumentih",
      "changelog": "* Bookmarks will be stored in yaml files."
    },
    {
      "language": "sr",
      "displayName": "Place markers",
      "description": "Dodatak za postavljanje markera na virtuelnim dokumentima",
      "changelog": "* Bookmarks will be stored in yaml files."
    },
    {
      "language": "ta",
      "displayName": "இடக் குறிப்பிகள்",
      "description": "HTML போன்ற நிகர் ஆவணங்களில் இடக் குறிப்பிகளை அமைப்பதற்கான கூட்டுறுப்பு ",
      "changelog": "* Bookmarks will be stored in yaml files."
    },
    {
      "language": "tr",
      "displayName": "Yerimleri",
      "description": "Sanal dokümanlar için yerimi eklentisi",
      "changelog": "* Bookmarks will be stored in yaml files."
    },
    {
      "language": "uk",
      "displayName": "Маркери місць",
      "description": "Додаток для маркування місць у певних віртуальних документах",
      "changelog": "* Bookmarks will be stored in yaml files."
    },
    {
      "language": "vi",
      "displayName": "Đánh dấu",
      "description": "Add-on thực hiện đánh dấu trên các tài liệu ảo",
      "changelog": "* Bookmarks will be stored in yaml files."
    },
    {
      "language": "zh_CN",
      "displayName": "位置标记",
      "description": "一个在特定虚拟文档中设置位置标记的插件",
      "changelog": "* Bookmarks will be stored in yaml files."
    },
    {
      "language": "zh_TW",
      "displayName": "Place markers",
      "description": "本附加元件可在使用瀏覽模式的文件中設定位置標記",
      "changelog": "* Bookmarks will be stored in yaml files."
    }
  ],
  "vtScanUrl": "https://www.virustotal.com/gui/file/7f46b0804a45272d54bf20b9abe0a522d635f131702561cdf4c4942e1ee47375",
  "scanResults": {
    "virusTotal": [
      {
        "_id": "7f46b0804a45272d54bf20b9abe0a522d635f131702561cdf4c4942e1ee47375",
        "_type": "file",
        "filecondis": {
          "dhash": "000000080d0c0400",
          "raw_md5": "0f84f9b8f8c1d3f24e84ae8079232722"
        },
        "first_submission_date": 1781447624,
        "last_analysis_results": {},
        "last_analysis_stats": {
          "confirmed-timeout": 0,
          "failure": 0,
          "harmless": 0,
          "malicious": 0,
          "suspicious": 0,
          "timeout": 0,
          "type-unsupported": 0,
          "undetected": 0
        },
        "last_modification_date": 1781447626,
        "last_submission_date": 1781447624,
        "md5": "8d73836bb4c37a5c33c01f807a7236c2",
        "names": [],
        "reputation": 0,
        "sha1": "1d0d7292bc2e4efbee6e05a1af14497b09e4c9b7",
        "sha256": "7f46b0804a45272d54bf20b9abe0a522d635f131702561cdf4c4942e1ee47375",
        "size": 433622,
        "tags": [],
        "times_submitted": 1,
        "total_votes": {
          "harmless": 0,
          "malicious": 0
        },
        "type_description": "unknown",
        "type_tags": [],
        "unique_sources": 1
      }
    ]
  },
  "reviewUrl": "https://github.com/nvaccess/addon-datastore/discussions/2279"
}
