{"addonId": "clipContentsDesigner", "displayName": "Clip Contents Designer", "URL": "https://github.com/nvdaes/clipContentsDesigner/releases/download/29.1.0/clipContentsDesigner-29.1.0.nvda-addon", "description": "Extension pour g\u00e9rer le texte du presse-papiers.", "sha256": "18c268633f47f502d02707a19afdae26e170c91b5faa4a9039338378eedb9cea", "addonVersionName": "29.1.0", "addonVersionNumber": {"major": 29, "minor": 1, "patch": 0}, "minNVDAVersion": {"major": 2023, "minor": 2, "patch": 0}, "lastTestedVersion": {"major": 2024, "minor": 1, "patch": 0}, "channel": "beta", "publisher": "nvdaes", "sourceURL": "https://github.com/nvdaes/clipContentsDesigner/releases/tag/29.1.0", "license": "GPL v2", "homepage": "https://github.com/nvdaes/clipContentsDesigner", "licenseURL": "https://www.gnu.org/licenses/gpl-2.0.html", "reviewUrl": "https://github.com/nvaccess/addon-datastore/discussions/2025"}