{"addonId": "winMag", "displayName": "Windows Forst\u00f8rrelsesglas", "URL": "https://github.com/CyrilleB79/winMag/releases/download/V3.6/winMag-3.6.nvda-addon", "description": "Denne tilf\u00f8jelse forbedrer brugen af Windows Forst\u00f8rrelsesglas sammen med NVDA.", "sha256": "2448b7fa44efa3a313204dc6e9addb6f4ad5b8360989899bd78d9ba98988e12b", "addonVersionName": "3.6", "addonVersionNumber": {"major": 3, "minor": 6, "patch": 0}, "minNVDAVersion": {"major": 2019, "minor": 2, "patch": 1}, "lastTestedVersion": {"major": 2023, "minor": 3, "patch": 3}, "channel": "stable", "publisher": "Cyrille Bougot", "sourceURL": "https://github.com/CyrilleB79/winMag", "license": "GPL v2", "homepage": "https://github.com/CyrilleB79/winMag", "licenseURL": "https://www.gnu.org/licenses/gpl-2.0.html", "reviewUrl": "https://github.com/nvaccess/addon-datastore/discussions/2486"}