{"addonId": "inputLock", "displayName": "Giri\u015f kilidi", "URL": "https://github.com/jmdaweb/inputLock/releases/download/v1.12/inputLock-1.12.nvda-addon", "description": "Bu eklenti ile, tek bir hareket ya da tu\u015fa basarak giri\u015f ayg\u0131tlar\u0131n\u0131 kilitlemek ve kilidini a\u00e7mak m\u00fcmk\u00fcn.\nBu hareketi girdi hareketler ileti\u015fim kutusundan de\u011fi\u015ftirilebilir. ", "sha256": "597e217180438ab46903e48e11210a24d8b93af26ff15839777c91d3080959bc", "addonVersionName": "1.12", "addonVersionNumber": {"major": 1, "minor": 12, "patch": 0}, "minNVDAVersion": {"major": 2022, "minor": 4, "patch": 0}, "lastTestedVersion": {"major": 2024, "minor": 1, "patch": 0}, "channel": "stable", "publisher": "jmdaweb", "sourceURL": "https://github.com/jmdaweb/inputLock", "license": "GPL v2", "homepage": "https://github.com/jmdaweb/inputLock", "licenseURL": "https://www.gnu.org/licenses/gpl-2.0.html", "reviewUrl": "https://github.com/nvaccess/addon-datastore/discussions/2822"}