{"addonId": "urlShortener", "displayName": "BluetoothAudio", "URL": "https://github.com/nvdaes/urlShortener/releases/download/7.1.0/urlShortener-7.1.0.nvda-addon", "description": "Bluetooth Audio \u00e4r ett till\u00e4gg till NVDA som  f\u00f6rb\u00e4ttrar ljudkvalit\u00e9n n\u00e4r man anv\u00e4nder bluetoothh\u00f6rlurar eller bluetoothh\u00f6gtalare.", "sha256": "4988e539babbf1cb1fe8d283dbfa9e2c4b8d1a6af3ba88817c3c886988d147f1", "addonVersionName": "7.1.0", "addonVersionNumber": {"major": 7, "minor": 1, "patch": 0}, "minNVDAVersion": {"major": 2023, "minor": 1, "patch": 0}, "lastTestedVersion": {"major": 2023, "minor": 1, "patch": 0}, "channel": "beta", "publisher": "nvdaes", "sourceURL": "https://github.com/nvdaes/urlShortener/releases/tag/7.1.0", "license": "GPL v2", "homepage": "https://github.com/nvdaes/urlShortener", "licenseURL": "https://www.gnu.org/licenses/gpl-2.0.html"}