{"addonId": "controlUsageAssistant", "displayName": "Kontrol Kullan\u0131m Asistan\u0131", "URL": "https://github.com/nvdaes/controlUsageAssistant/releases/download/20231028.2.0/controlUsageAssistant-20231028.2.0.nvda-addon", "description": "Odaklanan kontrolle nas\u0131l etkile\u015fim kurabilece\u011finizle ilgili yard\u0131m alman\u0131z\u0131 sa\u011flar, bilgisayar ve NVDA'y\u0131 yeni kullanmaya ba\u015flayanlar i\u00e7in faydal\u0131 olabilir.\n\tOdaklanan kontrolle ilgili, \u00f6rne\u011fin bir tablo, liste, men\u00fc vb, k\u0131sa bir yard\u0131m almak i\u00e7in NvDA+H tu\u015flar\u0131na bas\u0131n.", "sha256": "76ebfdc8d6589ff3dc0ed06fd02698dd8851def9e2db71e938ee0a011a86c5e4", "addonVersionName": "20231028.2.0", "addonVersionNumber": {"major": 20231028, "minor": 2, "patch": 0}, "minNVDAVersion": {"major": 2023, "minor": 2, "patch": 0}, "lastTestedVersion": {"major": 2024, "minor": 1, "patch": 0}, "channel": "beta", "publisher": "nvdaes", "sourceURL": "https://github.com/nvdaes/controlUsageAssistant/releases/tag/20231028.2.0", "license": "GPL v2", "homepage": "https://github.com/nvdaes/controlUsageAssistant", "licenseURL": "https://www.gnu.org/licenses/gpl-2.0.html", "reviewUrl": "https://github.com/nvaccess/addon-datastore/discussions/2020"}