{"addonId": "landropPlus", "displayName": "R\u00fdchly preklada\u010d", "URL": "https://github.com/RPTools-org/landropPlus/releases/download/v2023.05.23/landropPlus-2023.05.23.nvda-addon", "description": "Tento doplnok preklad\u00e1 vybrat\u00fd text alebo text v schr\u00e1nke pomocou externej slu\u017eby.", "sha256": "886d03648c3a9f52b9827e9137a6ae68cc0ad0f57e588c33d103b695a0c875da", "addonVersionName": "2023.05.23", "addonVersionNumber": {"major": 2023, "minor": 5, "patch": 23}, "minNVDAVersion": {"major": 2019, "minor": 3, "patch": 0}, "lastTestedVersion": {"major": 2023, "minor": 2, "patch": 0}, "channel": "stable", "publisher": "plr.listes@rptools.org", "sourceURL": "https://github.com/RPTools-org/landropPlus", "license": "GPL v2", "homepage": "https://\u0013\u0013www.rptools.org/NVDA-Thunderbird/toContact.html", "licenseURL": "https://www.gnu.org/licenses/gpl-2.0.html"}