{"addonId": "ime_expressive", "displayName": "\u4e2d\u6587\u8f93\u5165\u6cd5\u652f\u6301", "URL": "https://github.com/nvdacn/ime_expressive/releases/download/2024.3.21/ime_expressive-2024.3.21.nvda-addon", "description": "\u8be5\u63d2\u4ef6\u4e3a NVDA \u5c4f\u5e55\u9605\u8bfb\u5668\u63d0\u4f9b\u4e2d\u6587\u8f93\u5165\u6cd5\u6717\u8bfb\u652f\u6301\u3002\n\u4ece\u8f93\u5165\u4e60\u60ef\u548c\u6548\u7387\u65b9\u9762\u589e\u5f3a\u4e86 NVDA \u7528\u6237\u7684\u4e2d\u6587\u8f93\u5165\u4f53\u9a8c\u3002", "sha256": "df2588afa530d937a6c4ba7824cd2eb06b051aac89081ad0afedd6137d219965", "addonVersionName": "2024.3.21", "addonVersionNumber": {"major": 2024, "minor": 3, "patch": 21}, "minNVDAVersion": {"major": 2022, "minor": 1, "patch": 0}, "lastTestedVersion": {"major": 2024, "minor": 1, "patch": 0}, "channel": "stable", "publisher": "NVDACN", "sourceURL": "https://github.com/nvdacn/ime_expressive", "license": "GPL v2", "homepage": "https://www.nvdacn.com", "licenseURL": "https://www.gnu.org/licenses/gpl-2.0.html", "reviewUrl": "https://github.com/nvaccess/addon-datastore/discussions/2759"}