{
	"addonId": "unigetui",
	"displayName": "unigetui",
	"URL": "https://github.com/dave090679/unigetui/releases/download/0.6/unigetui-0.6.nvda-addon",
	"description": "improve accessibility of unigetui, a gui for winget and other package managers",
	"sha256": "68b83e34293274bef8c3f3dceb947d91eea583ac884c2288a5eeaeb8f8cf4566",
	"addonVersionName": "0.6",
	"addonVersionNumber": {
		"major": 0,
		"minor": 6,
		"patch": 0
	},
	"minNVDAVersion": {
		"major": 2022,
		"minor": 1,
		"patch": 0
	},
	"lastTestedVersion": {
		"major": 2025,
		"minor": 1,
		"patch": 0
	},
	"channel": "stable",
	"publisher": "David Parduhn",
	"sourceURL": "https://github.com/dave090679/unigetui",
	"license": "GPL v2",
	"homepage": "http://github.com/dave090679/unigetui/releases",
	"licenseURL": "https://www.gnu.org/licenses/gpl-2.0.html",
	"submissionTime": 1761735502000,
	"translations": [
		{
			"language": "de",
			"displayName": "unigetui",
			"description": "Verbesserung der Zugänglichkeit von UniGetui, einer GUI für Winget und andere Paketmanager"
		}
	]
}