{
	"addonId": "enhancedAnnotations",
	"displayName": "Enhanced Annotations",
	"URL": "https://github.com/nvdaes/enhancedAnnotations/releases/download/7.0.0/enhancedAnnotations-7.0.0.nvda-addon",
	"description": "Adds ability to move the cursor to additional details, and back to the original element, in browse mode.\n\tThis has been requested at\n\thttps://github.com/nvaccess/nvda/issues/13940\n\t",
	"sha256": "32a6c817df57417957834a50562f634d61bd9e70e234066bc2faa0a3c4440b81",
	"addonVersionName": "7.0.0",
	"addonVersionNumber": {
		"major": 7,
		"minor": 0,
		"patch": 0
	},
	"minNVDAVersion": {
		"major": 2023,
		"minor": 1,
		"patch": 0
	},
	"lastTestedVersion": {
		"major": 2023,
		"minor": 1,
		"patch": 0
	},
	"channel": "stable",
	"publisher": "nvdaes",
	"sourceURL": "https://github.com/nvdaes/enhancedAnnotations/releases/tag/7.0.0",
	"license": "GPL v2",
	"homepage": "https://github.com/nvdaes/enhancedAnnotations",
	"licenseURL": "https://www.gnu.org/licenses/gpl-2.0.html"
}