{"addonId": "addonUpdater", "displayName": "Updater f\u00fcr NVDA-Erweiterungen", "URL": "https://github.com/josephsl/addonUpdater/releases/download/23.12/addonUpdater-23.12.nvda-addon", "description": "\"Proof of Concept\"-Implementierung der Funktion f\u00fcr die Aktualisierung von NVDA-Erweiterung (NVDA-Kernproblem #3208)", "sha256": "4f5b5d762339318f10dafb824a329c4b41fe003d44cf52a8de59540191e8563e", "addonVersionName": "23.12", "addonVersionNumber": {"major": 23, "minor": 12, "patch": 0}, "minNVDAVersion": {"major": 2023, "minor": 1, "patch": 0}, "lastTestedVersion": {"major": 2023, "minor": 3, "patch": 0}, "channel": "stable", "publisher": "josephsl", "sourceURL": "https://github.com/josephsl/addonUpdater", "license": "GPL v2", "homepage": "https://addons.nvda-project.org/", "licenseURL": "https://www.gnu.org/licenses/gpl-2.0.html", "reviewUrl": "https://github.com/nvaccess/addon-datastore/discussions/2072#discussioncomment-7664412"}