{"addonId": "dayOfTheWeek", "displayName": "\u0414\u0435\u043d\u044c \u0442\u0438\u0436\u043d\u044f", "URL": "https://github.com/abdel792/dayOfTheWeek/releases/download/v25.04.19-2-beta/dayOfTheWeek-20250419.0.3.nvda-addon", "description": "\u0417 \u0446\u0438\u043c \u0434\u043e\u0434\u0430\u0442\u043a\u043e\u043c \u0432\u0438 \u0437\u043d\u0430\u0442\u0438\u043c\u0435\u0442\u0435, \u043d\u0430 \u044f\u043a\u0438\u0439 \u0434\u0435\u043d\u044c \u0442\u0438\u0436\u043d\u044f \u043f\u0440\u0438\u043f\u0430\u0434\u0430\u0454 \u043f\u043e\u0442\u0440\u0456\u0431\u043d\u0430 \u0432\u0430\u043c \u0434\u0430\u0442\u0430.", "sha256": "0ba0a69cd35f1aa8b9172808c72ff1cfb259f40953ee4505c67623230aa25420", "addonVersionName": "20250419.0.3", "addonVersionNumber": {"major": 20250419, "minor": 0, "patch": 3}, "minNVDAVersion": {"major": 2019, "minor": 3, "patch": 0}, "lastTestedVersion": {"major": 2025, "minor": 1, "patch": 0}, "channel": "beta", "publisher": "abdel792", "sourceURL": "https://github.com/abdel792/dayOfTheWeek/", "license": "GPL v2", "homepage": "https://github.com/abdel792/dayOfTheWeek", "licenseURL": "https://www.gnu.org/licenses/gpl-2.0.html", "submissionTime": 1745093347000, "reviewUrl": "https://github.com/nvaccess/addon-datastore/discussions/2207", "vtScanUrl": "https://www.virustotal.com/gui/file/0ba0a69cd35f1aa8b9172808c72ff1cfb259f40953ee4505c67623230aa25420"}