{"addonId": "clipContentsDesigner", "displayName": "Upravljanje sadr\u017eajem me\u0111uspremnika", "URL": "https://github.com/nvdaes/clipContentsDesigner/releases/download/31.0.0/clipContentsDesigner-31.0.0.nvda-addon", "description": "Dodatak za upravljanje tekstom iz me\u0111uspremnika.", "sha256": "13749ec2c0902ba1e9f5a054f374580529ec5a7aacc3077e5bf6a971d3740555", "addonVersionName": "31.0.0", "addonVersionNumber": {"major": 31, "minor": 0, "patch": 0}, "minNVDAVersion": {"major": 2023, "minor": 2, "patch": 0}, "lastTestedVersion": {"major": 2024, "minor": 1, "patch": 0}, "channel": "stable", "publisher": "nvdaes", "sourceURL": "https://github.com/nvdaes/clipContentsDesigner/releases/tag/31.0.0", "license": "GPL v2", "homepage": "https://github.com/nvdaes/clipContentsDesigner", "licenseURL": "https://www.gnu.org/licenses/gpl-2.0.html", "reviewUrl": "https://github.com/nvaccess/addon-datastore/discussions/2025"}