{"addonId": "numpadNavMode", "displayName": "Say\u0131sal Tu\u015f Tak\u0131m\u0131 gezinme Modu", "URL": "https://github.com/opensourcesys/numpadNavMode/releases/download/v23.1.7/numpadNavMode-23.1.7.nvda-addon", "description": "NVDA gezinme modu ile Windows gezinme modu aras\u0131nda say\u0131sal tu\u015f tak\u0131m\u0131n\u0131n de\u011fi\u015ftirilmesine izin verir.\n\u00d6zellikle daha \u00f6nce Jaws kullananlar i\u00e7in kullan\u0131\u015fl\u0131d\u0131r; veya diz\u00fcst\u00fc bilgisayar modunu tercih eden ancak say\u0131sal tu\u015f tak\u0131m\u0131na sahip olan ve onu ok tu\u015flar\u0131 vb. i\u00e7in kullanmak isteyen diz\u00fcst\u00fc bilgisayar kullan\u0131c\u0131lar\u0131 i\u00e7in.\nEklenti ayr\u0131ca, NVDA'y\u0131 ba\u015flat\u0131rken veya profilleri de\u011fi\u015ftirirken Numara kilidi tu\u015funun durumunun kontrol\u00fcn\u00fc sa\u011flar.", "sha256": "313b430e7126571d3187fe3539249426b78e6311d8611dc01ab69528d0a2d584", "addonVersionName": "23.1.7", "addonVersionNumber": {"major": 23, "minor": 1, "patch": 7}, "minNVDAVersion": {"major": 2019, "minor": 3, "patch": 0}, "lastTestedVersion": {"major": 2023, "minor": 1, "patch": 0}, "channel": "stable", "publisher": "Luke Davis (Open Source Systems)", "sourceURL": "https://github.com/opensourcesys/numpadNavMode/", "license": "GPL v2", "homepage": "https://github.com/opensourcesys/numpadNavMode/blob/master/readme.md", "licenseURL": "https://www.gnu.org/licenses/gpl-2.0.html"}