{"addonId": "CloudVision", "displayName": "CloudVision", "URL": "https://github.com/alekssamos/cloudvision/releases/download/v5.0.2-beta/CloudVision.nvda-addon", "description": "AI teknolojisindeki son geli\u015fmelerden yararlanarak g\u00f6r\u00fcnt\u00fcleri tan\u0131mlamaya y\u00f6nelik bir eklenti. Explorer'da bir nesnenin veya se\u00e7ilen dosyan\u0131n a\u00e7\u0131klamas\u0131n\u0131 almak i\u00e7in NVDA+Control+I tu\u015flar\u0131na bas\u0131n, h\u0131zl\u0131ca iki kez basarsan\u0131z sanal bir g\u00f6r\u00fcnt\u00fcleyici a\u00e7\u0131l\u0131r.", "sha256": "50b51d081348f091faa55f54da28d0d183f35516609d1a812f9e3b99efec6631", "addonVersionName": "5.0.2", "addonVersionNumber": {"major": 5, "minor": 0, "patch": 2}, "minNVDAVersion": {"major": 2019, "minor": 1, "patch": 0}, "lastTestedVersion": {"major": 2025, "minor": 1, "patch": 0}, "channel": "beta", "publisher": "alekssamos", "sourceURL": "https://github.com/alekssamos/cloudvision", "license": "GPL v2", "homepage": "https://visionbot.ru/addon/", "licenseURL": "https://www.gnu.org/licenses/gpl-2.0.html", "submissionTime": 1748874875000, "reviewUrl": "https://github.com/nvaccess/addon-datastore/discussions/4695", "vtScanUrl": "https://www.virustotal.com/gui/file/50b51d081348f091faa55f54da28d0d183f35516609d1a812f9e3b99efec6631"}